README.md
setup.py
whalewisdom_holdings/__init__.py
whalewisdom_holdings/holdings.py
whalewisdom_holdings.egg-info/PKG-INFO
whalewisdom_holdings.egg-info/SOURCES.txt
whalewisdom_holdings.egg-info/dependency_links.txt
whalewisdom_holdings.egg-info/requires.txt
whalewisdom_holdings.egg-info/top_level.txt