Metadata-Version: 2.1
Name: whalewisdom-holdings
Version: 0.0.2
Summary: Package for retrieving holdings data from whalewisdom's api
Home-page: https://github.com/BBScholar/whalewisdom_holdings
Author: Ben Scholar
Author-email: bens@digitalman.com
License: UNKNOWN
Platform: UNKNOWN
Classifier: Programming Language :: Python :: 3
Classifier: License :: OSI Approved :: MIT License
Classifier: Operating System :: OS Independent
Requires-Python: >=3.5
